slimeface-2024.9.27.dist-info/LICENSE
slimeface-2024.9.27.dist-info/METADATA
slimeface-2024.9.27.dist-info/RECORD
slimeface-2024.9.27.dist-info/WHEEL
slimeface-2024.9.27.dist-info/top_level.txt
slimeface.libs/libgomp-a34b3233.so.1.0.0
slimeface/libfacedetection.so
slimeface/libfacedetection.so.v0.0.3
slimeface/slimeface.cpython-37m-x86_64-linux-gnu.so
slimeface/__init__.py
